<keyframes>
    <key>
        <easefunc>1</easefunc>
        <easetype>2</easetype>
        <time>00:00:00:000</time>
        <value>0.000000000</value>
    </key>
    <key>
        <easefunc>0</easefunc>
        <easetype>0</easetype>
        <time>00:00:31:250</time>
        <value>1.000000000</value>
    </key>
    <key>
        <easefunc>0</easefunc>
        <easetype>0</easetype>
        <time>00:01:59:687</time>
        <value>1.000000000</value>
    </key>
    <key>
        <easefunc>2</easefunc>
        <easetype>0</easetype>
        <time>00:02:46:053</time>
        <value>0.000000000</value>
    </key>
</keyframes>
